xia_engine_neo4j/__init__.py
xia_engine_neo4j/engine.cpython-39-darwin.so
xia_engine_neo4j-0.1.1.dist-info/LICENSE.txt
xia_engine_neo4j-0.1.1.dist-info/METADATA
xia_engine_neo4j-0.1.1.dist-info/WHEEL
xia_engine_neo4j-0.1.1.dist-info/top_level.txt
xia_engine_neo4j-0.1.1.dist-info/RECORD
