Metadata-Version: 2.1
Name: xia-engine-neo4j
Version: 0.1.1
Summary: UNKNOWN
Home-page: https://develop.x-i-a.com/docs/xia-engine-neo4j/0.1.1/index.html
Author: X-I-A
Author-email: admin@x-i-a.com
License: UNKNOWN
Platform: UNKNOWN
Requires-Python: >=3.9
License-File: LICENSE.txt
Requires-Dist: neo4j
Requires-Dist: xia-fields
Requires-Dist: xia-engine
Requires-Dist: xia-engine-cypher
